{
  "meta": {
    "title": "17250 Omaha",
    "subtitle": "Manager view",
    "summary_line": "11 flags this week",
    "back_label": "Dashboard",
    "back_url": "index.html",
    "total_flags": 11
  },
  "tiles": [
    {
      "id": "tardiness",
      "title": "Tardiness",
      "is_mock": false,
      "columns": [
        "Date",
        "Employee",
        "Scheduled",
        "Actual",
        "Min Late"
      ],
      "rows": [
        [
          "2026-06-15",
          "Christian Van Dam",
          "9:00 AM",
          "9:48 AM",
          "48"
        ],
        [
          "2026-06-16",
          "Clark",
          "10:00 AM",
          "12:21 PM",
          "141"
        ],
        [
          "2026-06-17",
          "Christian Van Dam",
          "9:00 AM",
          "9:17 AM",
          "17"
        ]
      ],
      "count": 3
    },
    {
      "id": "long-shifts",
      "title": "Long Shifts",
      "is_mock": false,
      "columns": [
        "Employee",
        "Date",
        "Start",
        "End",
        "Hours",
        "Weekly",
        "Triggered"
      ],
      "rows": [],
      "count": 0
    },
    {
      "id": "short-shifts",
      "title": "Short Shifts",
      "is_mock": false,
      "columns": [
        "Employee",
        "Date",
        "Start",
        "End",
        "Hours"
      ],
      "rows": [],
      "count": 0
    },
    {
      "id": "over-40-vacation",
      "title": "Over 40 + Vacation",
      "is_mock": false,
      "columns": [
        "Employee",
        "Worked",
        "Leave",
        "Total",
        "Overage"
      ],
      "rows": [],
      "count": 0
    },
    {
      "id": "unapproved-timecards",
      "title": "Unapproved Timecards",
      "is_mock": false,
      "columns": [
        "Employee",
        "Date",
        "Hours"
      ],
      "rows": [
        [
          "Christian Van Dam",
          "Mon Jun 15",
          "8.32"
        ],
        [
          "Cieron Hampson",
          "Mon Jun 15",
          "8.23"
        ],
        [
          "Clark",
          "Tue Jun 16",
          "5.77"
        ],
        [
          "Noah Strako",
          "Tue Jun 16",
          "8.20"
        ],
        [
          "Cieron Hampson",
          "Tue Jun 16",
          "8.23"
        ],
        [
          "Christian Van Dam",
          "Wed Jun 17",
          "8.72"
        ],
        [
          "Clark",
          "Wed Jun 17",
          "7.97"
        ],
        [
          "Noah Strako",
          "Wed Jun 17",
          "8.20"
        ]
      ],
      "count": 8
    }
  ]
}