{
  "meta": {
    "title": "17250 Omaha",
    "subtitle": "Manager view",
    "summary_line": "8 flags this week",
    "back_label": "Dashboard",
    "back_url": "index.html",
    "total_flags": 8
  },
  "tiles": [
    {
      "id": "tardiness",
      "title": "Tardiness",
      "is_mock": false,
      "columns": [
        "Date",
        "Employee",
        "Scheduled",
        "Actual",
        "Min Late"
      ],
      "rows": [
        [
          "2026-07-06",
          "Christian Van Dam",
          "9:00 AM",
          "9:50 AM",
          "50"
        ],
        [
          "2026-07-10",
          "Christian Van Dam",
          "9:00 AM",
          "9:17 AM",
          "17"
        ],
        [
          "2026-07-11",
          "Christian Van Dam",
          "9:00 AM",
          "9:46 AM",
          "46"
        ],
        [
          "2026-07-11",
          "Clark",
          "10:00 AM",
          "10:14 AM",
          "14"
        ]
      ],
      "count": 4
    },
    {
      "id": "long-shifts",
      "title": "Long Shifts",
      "is_mock": false,
      "columns": [
        "Employee",
        "Date",
        "Start",
        "End",
        "Hours",
        "Weekly",
        "Triggered"
      ],
      "rows": [
        [
          "Noah Strako",
          "Tue Jul 7",
          "7:58 AM",
          "6:03 PM",
          "10.08",
          "91.21 (OT)",
          "OT"
        ]
      ],
      "count": 1
    },
    {
      "id": "short-shifts",
      "title": "Short Shifts",
      "is_mock": false,
      "columns": [
        "Employee",
        "Date",
        "Start",
        "End",
        "Hours"
      ],
      "rows": [],
      "count": 0
    },
    {
      "id": "over-40-vacation",
      "title": "Over 40 + Vacation",
      "is_mock": false,
      "columns": [
        "Employee",
        "Worked",
        "Leave",
        "Total",
        "Overage"
      ],
      "rows": [],
      "count": 0
    },
    {
      "id": "unapproved-timecards",
      "title": "Unapproved Timecards",
      "is_mock": false,
      "columns": [
        "Employee",
        "Date",
        "Hours"
      ],
      "rows": [
        [
          "Clark",
          "Sun Jul 12",
          "5.23"
        ],
        [
          "Noah Strako",
          "Sun Jul 12",
          "6.18"
        ],
        [
          "Cieron Hampson",
          "Sun Jul 12",
          "5.03"
        ]
      ],
      "count": 3
    }
  ]
}