{
  "meta": {
    "title": "Philadelphia - 1702 Walnut",
    "subtitle": "Manager view",
    "summary_line": "4 flags this week",
    "back_label": "Dashboard",
    "back_url": "index.html",
    "total_flags": 4
  },
  "tiles": [
    {
      "id": "tardiness",
      "title": "Tardiness",
      "is_mock": false,
      "columns": [
        "Date",
        "Employee",
        "Scheduled",
        "Actual",
        "Min Late"
      ],
      "rows": [
        [
          "2026-07-01",
          "Franco Bailey",
          "9:30 AM",
          "9:38 AM",
          "8"
        ],
        [
          "2026-07-02",
          "Celina Bryant",
          "8:30 AM",
          "8:50 AM",
          "20"
        ],
        [
          "2026-07-03",
          "Celina Bryant",
          "9:30 AM",
          "9:44 AM",
          "14"
        ]
      ],
      "count": 3
    },
    {
      "id": "long-shifts",
      "title": "Long Shifts",
      "is_mock": false,
      "columns": [
        "Employee",
        "Date",
        "Start",
        "End",
        "Hours",
        "Weekly",
        "Triggered"
      ],
      "rows": [],
      "count": 0
    },
    {
      "id": "short-shifts",
      "title": "Short Shifts",
      "is_mock": false,
      "columns": [
        "Employee",
        "Date",
        "Start",
        "End",
        "Hours"
      ],
      "rows": [
        [
          "Franco Bailey",
          "Thu Jul 2",
          "5:49 PM",
          "6:03 PM",
          "0.23"
        ]
      ],
      "count": 1
    },
    {
      "id": "over-40-vacation",
      "title": "Over 40 + Vacation",
      "is_mock": false,
      "columns": [
        "Employee",
        "Worked",
        "Leave",
        "Total",
        "Overage"
      ],
      "rows": [],
      "count": 0
    },
    {
      "id": "unapproved-timecards",
      "title": "Unapproved Timecards",
      "is_mock": false,
      "columns": [
        "Employee",
        "Date",
        "Hours"
      ],
      "rows": [],
      "count": 0
    }
  ]
}