{
  "meta": {
    "title": "Weekly Trends",
    "subtitle": "Most recent week vs. 2026 average",
    "summary_line": "7 metrics tracked",
    "last_refreshed_display": "Data through Thu Jul 2, 2026",
    "back_label": "Dashboard",
    "back_url": "index.html"
  },
  "columns": [
    "Metric",
    "Jun 22 \u2013 Jun 28",
    "2026 Avg",
    "Trend"
  ],
  "groups": [
    {
      "shop": "",
      "manager": "",
      "count": 7,
      "rows": [
        [
          "Manager Attendance",
          "12",
          "20.1",
          "\u2193 Better"
        ],
        [
          "Unapproved Timecards",
          "5",
          "0.0",
          "-"
        ],
        [
          "Manual Punches % (week)",
          "10.5%",
          "21.3%",
          "\u2193 Better"
        ],
        [
          "Tardiness",
          "104",
          "101.3",
          "\u2192 Stable"
        ],
        [
          "Penalty Pay (shops)",
          "2",
          "2.8",
          "\u2193 Better"
        ],
        [
          "Schedule Publication",
          "7",
          "-",
          "-"
        ],
        [
          "Pending Leave",
          "3",
          "-",
          "-"
        ]
      ]
    }
  ]
}